[{"from": "Athletic Bilbao", "name": "Fernando Llorente", "currency": "Euro", "value": "Free", "to": "Juventus", "date": "24 January 2013"}, {"from": "Napoli", "name": "Hugo Campagnaro", "currency": "Euro", "value": "Free", "to": "Internazionale", "date": "1 February 2013"}, {"from": "Chievo", "name": "Marco Andreolli", "currency": "Euro", "value": "Free", "to": "Internazionale", "date": "20 February 2013"}, {"from": "Lazio", "name": "Juan Pablo Carrizo", "currency": "Euro", "value": "Free", "to": "Internazionale", "date": "14 March 2013"}, {"from": "Cerro", "name": "Gonzalo Mastriani", "currency": "Euro", "value": "Free", "to": "Parma", "date": "20 March 2013"}, {"from": "Anderlecht", "name": "Oleksandr Yakovenko", "currency": "Euro", "value": "Free", "to": "Fiorentina", "date": "22 May 2013"}, {"from": "Paris Saint-Germain", "name": "Abdallah Yaisien", "currency": "Euro", "value": "Undisclosed", "to": "Bologna", "date": "28 May 2013"}, {"from": "Udinese", "name": "Daniele Padelli", "currency": "Euro", "value": "Free", "to": "Torino", "date": "29 May 2013"}, {"from": "Bolton Wanderers", "name": "Marcos Alonso", "currency": "Euro", "value": "Free", "to": "Fiorentina", "date": "31 May 2013"}, {"from": "Roma", "name": "Maarten Stekelenburg", "currency": "Euro", "value": 5600000, "to": "Fulham", "date": "5 June 2013"}, {"from": "Bologna", "name": "Nicola Capellini", "currency": "Euro", "value": "Free", "to": "Cesena", "date": "13 June 2013"}, {"from": "M\u00e1laga", "name": "Joaqu\u00edn", "currency": "Euro", "value": "Undisclosed", "to": "Fiorentina", "date": "13 June 2013"}, {"from": "Standard Li\u00e8ge", "name": "Yohan Tavares", "currency": "Euro", "value": "Undisclosed", "to": "Chievo", "date": "14 June 2013"}, {"from": "Udinese", "name": "Antonio Candreva", "currency": "Euro", "value": "Co-ownership, ", "to": "Lazio", "date": "17 June 2013"}, {"from": "Internazionale", "name": "Matteo Bianchetti", "currency": "Euro", "value": "Co-ownership", "to": "Verona", "date": "17 June 2013"}, {"from": "Torino", "name": "Alessandro Agostini", "currency": "Euro", "value": "Undisclosed", "to": "Verona", "date": "17 June 2013"}, {"from": "Catania", "name": "Raphael Martinho", "currency": "Euro", "value": "Co-ownership", "to": "Verona", "date": "17 June 2013"}, {"from": "Albinoleffe", "name": "Simon Laner", "currency": "Euro", "value": "Co-ownership ", "to": "Verona", "date": "17 June 2013"}, {"from": "Atalanta", "name": "Federico Peluso", "currency": "Euro", "value": 4800000, "to": "Juventus", "date": "17 June 2013"}, {"from": "Udinese", "name": "Pablo Armero", "currency": "Euro", "value": "Co-ownership", "to": "Napoli", "date": "18 June 2013"}, {"from": "Levante", "name": "Gustavo Mun\u00faa", "currency": "Euro", "value": "Free", "to": "Fiorentina", "date": "18 June 2013"}, {"from": "Genoa", "name": "Davide Bertoncini", "currency": "Euro", "value": "Co-ownership", "to": "Frosinone", "date": "19 June 2013"}, {"from": "Livorno", "name": "Antonio Piccolo", "currency": "Euro", "value": "Co-ownership", "to": "Lanciano", "date": "19 June 2013"}, {"from": "Young Boys", "name": "Alexander Farnerud", "currency": "Euro", "value": "Undisclosed", "to": "Torino", "date": "19 June 2013"}, {"from": "Sampdoria", "name": "Fabrizio Cacciatore", "currency": "Euro", "value": "Co-ownership ", "to": "Verona", "date": "19 June 2013"}, {"from": "Novara", "name": "Bruno Fernandes", "currency": "Euro", "value": "Co-ownership ", "to": "Udinese", "date": "19 June 2013"}, {"from": "Palermo", "name": "Francesco Della Rocca", "currency": "Euro", "value": "Loan (between co-owner)", "to": "Bologna", "date": "20 June 2013"}, {"from": "Sampdoria", "name": "Francesco Signori", "currency": "Euro", "value": "Co-ownership", "to": "Modena", "date": "20 June 2013"}, {"from": "Cesena", "name": "Yohan Benalouane", "currency": "Euro", "value": "Co-ownership", "to": "Parma", "date": "20 June 2013"}, {"from": "Frosinone", "name": "Leandro Campagna", "currency": "Euro", "value": "Co-ownership, ", "to": "Parma", "date": "20 June 2013"}, {"from": "Internazionale", "name": "Giulio Donati", "currency": "Euro", "value": "Undisclosed", "to": "Bayer Leverkusen", "date": "21 June 2013"}, {"from": "Genoa", "name": "Mattia Destro", "currency": "Euro", "value": 4500000, "to": "Roma", "date": "21 June 2013"}, {"from": "Internazionale", "name": "Cristiano Biraghi", "currency": "Euro", "value": "Co-ownership", "to": "Cittadella", "date": "21 June 2013"}, {"from": "Cesena", "name": "Damjan \u0110okovi\u0107", "currency": "Euro", "value": "Co-ownership (swap with Ingegneri)", "to": "Bologna", "date": "24 June 2013"}, {"from": "Bologna", "name": "Andrea Ingegneri", "currency": "Euro", "value": "Co-ownership (swap with \u0110okovi\u0107)", "to": "Cesena", "date": "24 June 2013"}, {"from": "PSV", "name": "Dries Mertens", "currency": "Euro", "value": "Undisclosed", "to": "Napoli", "date": "25 June 2013"}, {"from": "Palermo", "name": "Massimo Donati", "currency": "Euro", "value": "Undisclosed", "to": "Verona", "date": "25 June 2013"}, {"from": "Pe\u00f1arol", "name": "Guillermo Rodriguez", "currency": "Euro", "value": "Undisclosed", "to": "Torino", "date": "26 June 2013"}, {"from": "Manchester City", "name": "Carlos Tevez", "currency": "Euro", "value": 9000000, "to": "Juventus", "date": "26 June 2013"}, {"from": "Ascoli", "name": "Daniele Gragnoli", "currency": "Euro", "value": "Co-ownership, ", "to": "Parma", "date": "27 June 2013"}, {"from": "Parma", "name": "Emiliano Storani", "currency": "Euro", "value": "Co-ownership, ", "to": "Ascoli", "date": "27 June 2013"}, {"from": "Chievo", "name": "Kamil Vacek", "currency": "Euro", "value": "Loan", "to": "Sparta Prague", "date": "27 June 2013"}, {"from": "Pe\u00f1arol", "name": "Alejandro Gonz\u00e1lez", "currency": "Euro", "value": "Undisclosed", "to": "Verona", "date": "28 June 2013"}, {"from": "Parma", "name": "Andres Sampedro", "currency": "Euro", "value": "Loan", "to": "Mineros", "date": "28 June 2013"}, {"from": "Parma", "name": "M\u00e1rio Rui", "currency": "Euro", "value": "Co-ownership, ", "to": "Empoli", "date": "28 June 2013"}, {"from": "Cesena", "name": "Marco Paolini", "currency": "Euro", "value": "Co-ownership, ", "to": "Parma", "date": "29 June 2013"}, {"from": "Parma", "name": "Davide Adorni", "currency": "Euro", "value": "Co-ownership, ", "to": "Cesena", "date": "29 June 2013"}, {"from": "Parma", "name": "Milo\u0161 Malivojevi\u0107", "currency": "Euro", "value": "Co-ownership, ", "to": "Vicenza", "date": "29 June 2013"}, {"from": "Vicenza", "name": "Mattia Sandrini", "currency": "Euro", "value": "Co-ownership, ", "to": "Parma", "date": "29 June 2013"}, {"from": "Girona", "name": "Carlos Javier Acu\u00f1a", "currency": "Euro", "value": "Undisclosed", "to": "Udinese", "date": "29 June 2013"}, {"from": "Udinese", "name": "Carlos Javier Acu\u00f1a", "currency": "Euro", "value": "Loan", "to": "Watford", "date": "29 June 2013"}, {"from": "Parma", "name": "Fabio Lebran", "currency": "Euro", "value": "Co-ownership, ", "to": "Crotone", "date": "29 June 2013"}, {"from": "Crotone", "name": "Massimo Loviso", "currency": "Euro", "value": "Co-ownership, ", "to": "Parma", "date": "29 June 2013"}, {"from": "Cittadella", "name": "Alex Cordaz", "currency": "Euro", "value": "Free", "to": "Parma", "date": "29 June 2013"}, {"from": "Parma", "name": "Daniel Ciofani", "currency": "Euro", "value": "Co-ownership, ", "to": "Frosinone", "date": "30 June 2013"}, {"from": "Parma", "name": "Solomon Enow", "currency": "Euro", "value": 1000000, "to": "Gorica", "date": "30 June 2013"}, {"from": "Sampdoria", "name": "Emanuele Testardi", "currency": "Euro", "value": "Loan", "to": "Honv\u00e9d", "date": "1 July 2013"}, {"from": "Sampdoria", "name": "Jonathan Rossini", "currency": "Euro", "value": "Co-ownership, ", "to": "Sassuolo", "date": "1 July 2013"}, {"from": "Catania", "name": "Luca Calapai", "currency": "Euro", "value": "Co-ownership", "to": "Modena", "date": "1 July 2013"}, {"from": "Roma", "name": "Luca Antei", "currency": "Euro", "value": "Co-ownership, ", "to": "Sassuolo", "date": "1 July 2013"}, {"from": "Roma", "name": "Matteo Politano", "currency": "Euro", "value": "Co-ownership, ", "to": "Pescara", "date": "1 July 2013"}, {"from": "Parma", "name": "Fabio Lebran", "currency": "Euro", "value": "Loan", "to": "Gorica", "date": "1 July 2013"}, {"from": "Parma", "name": "Gianluca Lapadula", "currency": "Euro", "value": "Loan", "to": "Gorica", "date": "1 July 2013"}, {"from": "Parma", "name": "Alex Cordaz", "currency": "Euro", "value": "Loan", "to": "Gorica", "date": "1 July 2013"}, {"from": "Parma", "name": "Bright Addae", "currency": "Euro", "value": "Loan", "to": "Gorica", "date": "1 July 2013"}, {"from": "Sassuolo", "name": "Gennaro Troianiello", "currency": "Euro", "value": "Undisclosed", "to": "Palermo", "date": "2 July 2013"}, {"from": "Palermo", "name": "Jasmin Kurti\u0107", "currency": "Euro", "value": "Co-ownership", "to": "Sassuolo", "date": "2 July 2013"}, {"from": "Juventus", "name": "Lauren\u0163iu Br\u0103nescu", "currency": "Euro", "value": "Loan", "to": "Juve Stabia", "date": "2 July 2013"}, {"from": "Genoa", "name": "Riccardo Improta", "currency": "Euro", "value": "Loan", "to": "Chievo", "date": "2 July 2013"}, {"from": "Como", "name": "Luca Tremolada", "currency": "Euro", "value": "Co-ownership resolution", "to": "Internazionale", "date": "2 July 2013"}, {"from": "Verona", "name": "Luca Ceccarelli", "currency": "Euro", "value": "Undisclosed", "to": "Spezia", "date": "3 July 2013"}, {"from": "Internazionale", "name": "Antonio Cassano", "currency": "Euro", "value": "Undisclosed", "to": "Parma", "date": "3 July 2013"}, {"from": "Chievo", "name": "Nicola Bellomo", "currency": "Euro", "value": "Undisclosed (transfer of co-ownership)", "to": "Chievo", "date": "3 July 2013"}, {"from": "Torino", "name": "Alfred Gomis", "currency": "Euro", "value": "Loan", "to": "Crotone", "date": "3 July 2013"}, {"from": "Genoa", "name": "Luka Krajnc", "currency": "Euro", "value": "Loan", "to": "Cesena", "date": "3 July 2013"}, {"from": "Parma", "name": "Nicola Russo", "currency": "Euro", "value": "Loan", "to": "Gubbio", "date": "3 July 2013"}, {"from": "Internazionale", "name": "Raffaele Di Gennaro", "currency": "Euro", "value": "Loan", "to": "Cittadella", "date": "3 July 2013"}, {"from": "Lazio", "name": "Ettore Mendicino", "currency": "Euro", "value": "Loan", "to": "Salernitana", "date": "4 July 2013"}, {"from": "Internazionale", "name": "Luca Tremolada", "currency": "Euro", "value": "Co-ownership", "to": "Varese", "date": "4 July 2013"}, {"from": "Bari", "name": "Idriz Toski\u0107", "currency": "Euro", "value": "Co-ownership", "to": "Chievo", "date": "4 July 2013"}, {"from": "Parma", "name": "Manuel Coppola", "currency": "Euro", "value": "Loan", "to": "Cesena", "date": "4 July 2013"}, {"from": "Pro Vercelli", "name": "Elio De Silvestro", "currency": "Euro", "value": "Co-ownership resolution", "to": "Juventus", "date": "5 July 2013"}, {"from": "Juventus", "name": "Nazzareno Belfasti", "currency": "Euro", "value": "Co-ownership", "to": "Pro Vercelli", "date": "5 July 2013"}, {"from": "Juventus", "name": "Giuseppe Ruggiero", "currency": "Euro", "value": "Co-ownership", "to": "Pro Vercelli", "date": "5 July 2013"}, {"from": "Juventus", "name": "Stefano Padovan", "currency": "Euro", "value": "Loan", "to": "Pescara", "date": "5 July 2013"}, {"from": "Chievo", "name": "Bojan Joki\u0107", "currency": "Euro", "value": "Free", "to": "Villarreal", "date": "5 July 2013"}, {"from": "Parma", "name": "Ishak Belfodil", "currency": "Euro", "value": "Co-ownership", "to": "Internazionale", "date": "5 July 2013"}, {"from": "Entella", "name": "Francesco Zampano", "currency": "Euro", "value": "Undisclosed", "to": "Verona", "date": "5 July 2013"}, {"from": "Entella", "name": "Daniele Borra", "currency": "Euro", "value": "Loan", "to": "Verona", "date": "5 July 2013"}, {"from": "Entella", "name": "Filippo De Col", "currency": "Euro", "value": "Co-ownership", "to": "Verona", "date": "5 July 2013"}, {"from": "Fiorentina", "name": "Luca Toni", "currency": "Euro", "value": "Free", "to": "Verona", "date": "5 July 2013"}, {"from": "Internazionale", "name": "Simone Pecorini", "currency": "Euro", "value": "Co-ownership", "to": "Cittadella", "date": "5 July 2013"}, {"from": "Verona", "name": "Emanuele Pesoli", "currency": "Euro", "value": "Undisclosed", "to": "Carpi", "date": "5 July 2013"}, {"from": "V\u00e9lez", "name": "Federico Freire", "currency": "Euro", "value": "Free", "to": "Catania", "date": "5 July 2013"}, {"from": "Internazionale", "name": "Denis Alibec", "currency": "Euro", "value": "Loan", "to": "Bologna", "date": "6 July 2013"}, {"from": "Lierse", "name": "Soufiane Bidaoui", "currency": "Euro", "value": "Free", "to": "Parma", "date": "6 July 2013"}, {"from": "Sporting B", "name": "Pedro Mendes", "currency": "Euro", "value": "Free", "to": "Parma", "date": "6 July 2013"}, {"from": "Red Star Belgrade", "name": "Filip Jankovi\u0107", "currency": "Euro", "value": "Free", "to": "Parma", "date": "6 July 2013"}, {"from": "Genoa", "name": "Eduardo Carvalho", "currency": "Euro", "value": "Loan", "to": "Braga", "date": "6 July 2013"}, {"from": "Karpaty Lviv", "name": "Danilo Avelar", "currency": "Euro", "value": "Undisclosed", "to": "Cagliari", "date": "6 July 2013"}, {"from": "Fiorentina", "name": "Boadu Acosty", "currency": "Euro", "value": "Loan", "to": "Chievo", "date": "6 July 2013"}, {"from": "Atalanta", "name": "Simone Magnaghi", "currency": "Euro", "value": "Loan", "to": "Entella", "date": "8 July 2013"}, {"from": "Bayern Munich", "name": "Mario G\u00f3mez", "currency": "Euro", "value": "Undisclosed", "to": "Fiorentina", "date": "8 July 2013"}, {"from": "PAS Giannina", "name": "Marios Ikonomou", "currency": "Euro", "value": "Undisclosed", "to": "Cagliari", "date": "8 July 2013"}, {"from": "Torino", "name": "Sergiu Suciu", "currency": "Euro", "value": "Loan", "to": "Juve Stabia", "date": "8 July 2013"}, {"from": null, "name": "Felipe", "currency": "Euro", "value": "Undisclosed", "to": "Parma", "date": "8 July 2013"}, {"from": "Roma", "name": "Matteo Brighi", "currency": "Euro", "value": "Undisclosed", "to": "Torino", "date": "8 July 2013"}, {"from": "Roma", "name": "Gianluca Curci", "currency": "Euro", "value": "Loan", "to": "Bologna", "date": "8 July 2013"}, {"from": "Roma", "name": "Marco D'Alessandro", "currency": "Euro", "value": "Loan", "to": "Cesena", "date": "8 July 2013"}, {"from": "Roma", "name": "Jos\u00e9 \u00c1ngel", "currency": "Euro", "value": "Loan", "to": "Real Sociedad", "date": "8 July 2013"}, {"from": "Toluca", "name": "Diego Novaretti", "currency": "Euro", "value": "Free", "to": "Lazio", "date": "8 July 2013"}, {"from": "Santos", "name": "Felipe Anderson", "currency": "Euro", "value": "Undisclosed", "to": "Lazio", "date": "9 July 2013"}, {"from": "Sampdoria", "name": "Simone Zaza", "currency": "Euro", "value": 3500000, "to": "Juventus", "date": "9 July 2013"}, {"from": "Sampdoria", "name": "Mauro Icardi", "currency": "Euro", "value": "Co-ownership", "to": "Internazionale", "date": "9 July 2013"}, {"from": "Juventus", "name": "Manolo Gabbiadini", "currency": "Euro", "value": 5500000, "to": "Juventus", "date": "9 July 2013"}, {"from": "Juventus", "name": "Simone Zaza", "currency": "Euro", "value": "Co-ownership, ", "to": "Sassuolo", "date": "9 July 2013"}, {"from": null, "name": "Francesco Acerbi", "currency": "Euro", "value": "Co-ownership ", "to": "Sassuolo", "date": "9 July 2013"}, {"from": "Sampdoria", "name": "Luca Rizzo", "currency": "Euro", "value": "Loan", "to": "Modena", "date": "9 July 2013"}, {"from": "Sampdoria", "name": "Stefano D'Agostino", "currency": "Euro", "value": "Loan", "to": "Pontedera", "date": "9 July 2013"}, {"from": "Polonia Warsaw", "name": "Pawe\u0142 Wszo\u0142ek", "currency": "Euro", "value": "Free", "to": "Sampdoria", "date": "9 July 2013"}, {"from": "Torino", "name": "Rolando Bianchi", "currency": "Euro", "value": "Free", "to": "Bologna", "date": "9 July 2013"}, {"from": "Genoa", "name": "Cesare Bovo", "currency": "Euro", "value": "Undisclosed", "to": "Torino", "date": "9 July 2013"}, {"from": "Novara", "name": "Luigi Giorgi", "currency": "Euro", "value": "Undisclosed", "to": "Atalanta", "date": "9 July 2013"}, {"from": "Atalanta", "name": "Valerio Nava", "currency": "Euro", "value": "Loan", "to": "Novara", "date": "9 July 2013"}, {"from": "Atalanta", "name": "Alberto Almici", "currency": "Euro", "value": "Loan", "to": "Cesena", "date": "9 July 2013"}, {"from": "Chievo", "name": "Amedeo Benedetti", "currency": "Euro", "value": "Loan", "to": "Lumezzane", "date": "9 July 2013"}, {"from": "Juventus", "name": "Alberto Masi", "currency": "Euro", "value": "Co-ownership, ", "to": "Ternana", "date": "9 July 2013"}, {"from": "Genoa", "name": "Alexandros Tzorvas", "currency": "Euro", "value": "Free", "to": "Apollon Smyrni", "date": "9 July 2013"}, {"from": "Internazionale", "name": "Francesco Bardi", "currency": "Euro", "value": "Loan", "to": "Livorno", "date": "9 July 2013"}, {"from": "Fiorentina", "name": "Cristiano Piccini", "currency": "Euro", "value": "Loan", "to": "Livorno", "date": "9 July 2013"}, {"from": "Internazionale", "name": "Marco Benassi", "currency": "Euro", "value": "Loan", "to": "Livorno", "date": "9 July 2013"}, {"from": "Roma", "name": "Paolo Frascatore", "currency": "Euro", "value": "Loan", "to": "Pescara", "date": "9 July 2013"}, {"from": "Catania", "name": "Giovanni Marchese", "currency": "Euro", "value": "Free", "to": "Genoa", "date": "10 July 2013"}, {"from": "Brescia", "name": "Sebastian De Maio", "currency": "Euro", "value": "Free", "to": "Genoa", "date": "10 July 2013"}, {"from": "Chievo", "name": "Lucas Finazzi", "currency": "Euro", "value": "Loan", "to": "Brescia", "date": "10 July 2013"}, {"from": "Udinese", "name": "Andrea Mazzarani", "currency": "Euro", "value": "Co-ownership", "to": "Modena", "date": "10 July 2013"}, {"from": "Fiorentina", "name": "Nii Nortey Ashong", "currency": "Euro", "value": "Loan", "to": "Spezia", "date": "10 July 2013"}, {"from": "Chievo", "name": "Matteo Solini", "currency": "Euro", "value": "Loan", "to": "Reggiana", "date": "10 July 2013"}, {"from": "Chievo", "name": "Valerio Anastasi", "currency": "Euro", "value": "Co-ownership", "to": "Reggiana", "date": "10 July 2013"}, {"from": "Reggiana", "name": "Federico Scappi", "currency": "Euro", "value": "Co-ownership", "to": "Chievo", "date": "10 July 2013"}, {"from": "Chievo", "name": "Federico Scappi", "currency": "Euro", "value": "Loan", "to": "Reggiana", "date": "10 July 2013"}, {"from": "Catania", "name": "Mario Paglialunga", "currency": "Euro", "value": "Undisclosed", "to": "Zaragoza", "date": "10 July 2013"}, {"from": "Dinamo Zagreb", "name": "Tin Jedvaj", "currency": "Euro", "value": "\u20ac5M", "to": "Roma", "date": "10 July 2013"}, {"from": "Parma", "name": "Alessandro Iacobucci", "currency": "Euro", "value": "Loan", "to": "Latina", "date": "10 July 2013"}, {"from": "Parma", "name": "Riccardo Brosco", "currency": "Euro", "value": "Loan", "to": "Latina", "date": "10 July 2013"}, {"from": "Chievo", "name": "Juri Cisotti", "currency": "Euro", "value": "Loan", "to": "Latina", "date": "10 July 2013"}, {"from": "Sampdoria", "name": "Massimo Volta", "currency": "Euro", "value": "Loan", "to": "Cesena", "date": "11 July 2013"}, {"from": "Genoa", "name": "Emiliano Moretti", "currency": "Euro", "value": "Undisclosed", "to": "Torino", "date": "11 July 2013"}, {"from": null, "name": "Giulio Migliaccio", "currency": "Euro", "value": "Undisclosed", "to": "Atalanta", "date": "11 July 2013"}, {"from": "Dinamo Bucure\u0219ti", "name": "Constantin Nica", "currency": "Euro", "value": "Undisclosed", "to": "Atalanta", "date": "11 July 2013"}, {"from": "Sampdoria", "name": "Andrea Poli", "currency": "Euro", "value": "Co-ownership", "to": "Milan", "date": "11 July 2013"}, {"from": "Milan", "name": "Bartosz Salamon", "currency": "Euro", "value": "Co-ownership", "to": "Sampdoria", "date": "11 July 2013"}, {"from": "Internazionale", "name": "Lukas Spendlhofer", "currency": "Euro", "value": "Loan", "to": "Varese", "date": "11 July 2013"}, {"from": "Atalanta", "name": "Simone Colombi", "currency": "Euro", "value": "Loan", "to": "Padova", "date": "11 July 2013"}, {"from": "Real Madrid", "name": "Jos\u00e9 Callej\u00f3n", "currency": "Euro", "value": "Undisclosed", "to": "Napoli", "date": "11 July 2013"}, {"from": "Santos", "name": "Rafael Cabral", "currency": "Euro", "value": "Undisclosed", "to": "Napoli", "date": "11 July 2013"}, {"from": "Livorno", "name": "Simone Dell'Agnello", "currency": "Euro", "value": "Loan", "to": "S\u00fcdtirol", "date": "11 July 2013"}, {"from": "Livorno", "name": "Andrea Molinelli", "currency": "Euro", "value": "Co-ownership, ", "to": "S\u00fcdtirol", "date": "11 July 2013"}, {"from": "Chievo", "name": "Caleb Ekuban", "currency": "Euro", "value": "Loan", "to": "S\u00fcdtirol", "date": "11 July 2013"}, {"from": "Torino", "name": "Angelo Ogbonna", "currency": "Euro", "value": 1300000, "to": "Juventus", "date": "11 July 2013"}, {"from": "Napoli", "name": "Giuseppe Fornito", "currency": "Euro", "value": "Loan", "to": "Pescara", "date": "11 July 2013"}, {"from": "Torino", "name": "Alen Stevanovi\u0107", "currency": "Euro", "value": "Loan", "to": "Palermo", "date": "11 July 2013"}, {"from": "Siena", "name": "Alessio Sestu", "currency": "Euro", "value": "Free", "to": "Chievo", "date": "11 July 2013"}, {"from": "Catania", "name": "Federico Moretti", "currency": "Euro", "value": "Loan", "to": "Spezia", "date": "11 July 2013"}, {"from": "Juve Stabia", "name": "Ivano Baldanzeddu", "currency": "Euro", "value": "Free", "to": "Verona", "date": "11 July 2013"}, {"from": "Crotone", "name": "Francesco Migliore", "currency": "Euro", "value": "Free", "to": "Verona", "date": "11 July 2013"}, {"from": "Parma", "name": "Stefan Ristovski", "currency": "Euro", "value": "Loan", "to": "Latina", "date": "11 July 2013"}, {"from": "Napoli", "name": "Omar El Kaddouri", "currency": "Euro", "value": "Loan", "to": "Torino", "date": "12 July 2013"}, {"from": "Fiorentina", "name": "Lorenzo De Silvestri", "currency": "Euro", "value": "Loan", "to": "Sampdoria", "date": "12 July 2013"}, {"from": "Internazionale", "name": "Raffaele Dalle Vedove", "currency": "Euro", "value": "Co-ownership", "to": "Lumezzane", "date": "12 July 2013"}, {"from": "Internazionale", "name": "Lorenzo Crisetig", "currency": "Euro", "value": "Loan", "to": "Crotone", "date": "12 July 2013"}, {"from": "Atalanta", "name": "Emanuele Suagher", "currency": "Euro", "value": "Loan", "to": "Crotone", "date": "12 July 2013"}, {"from": "Livorno", "name": "Simone Salviato", "currency": "Euro", "value": "Undisclosed", "to": "Novara", "date": "12 July 2013"}, {"from": "Genoa", "name": "Linus Hallenius", "currency": "Euro", "value": "Undisclosed", "to": "Aarau", "date": "12 July 2013"}, {"from": "Krasnodar", "name": "Pape Moussa Konat\u00e9", "currency": "Euro", "value": "Loan", "to": "Genoa", "date": "12 July 2013"}, {"from": "Juventus", "name": "Ciro Immobile", "currency": "Euro", "value": 2750000, "to": "Juventus", "date": "12 July 2013"}, {"from": "Chievo", "name": "Pablo Granoche", "currency": "Euro", "value": "Loan", "to": "Cesena", "date": "12 July 2013"}, {"from": "Fiorentina", "name": "Michele Camporese", "currency": "Euro", "value": "Loan", "to": "Cesena", "date": "12 July 2013"}, {"from": "Genoa", "name": "Moro Alhassan", "currency": "Euro", "value": "Loan", "to": "Cesena", "date": "12 July 2013"}, {"from": "Juventus", "name": "Matteo Liviero", "currency": "Euro", "value": "Loan", "to": "Carpi", "date": "12 July 2013"}, {"from": "Chievo", "name": "Radoslav Kirilov", "currency": "Euro", "value": "Loan", "to": "Carpi", "date": "12 July 2013"}, {"from": "Milan", "name": "Michelangelo Albertazzi", "currency": "Euro", "value": "Co-ownership", "to": "Verona", "date": "12 July 2013"}, {"from": "Atalanta", "name": "Nadir Minotti", "currency": "Euro", "value": "Loan", "to": "Lanciano", "date": "12 July 2013"}, {"from": "Internazionale", "name": "Rodrigo Alborno", "currency": "Euro", "value": "Loan", "to": "Cittadella", "date": "12 July 2013"}, {"from": "Dinamo Zagreb", "name": "\u0160ime Vrsaljko", "currency": "Euro", "value": "Undisclosed", "to": "Genoa", "date": "12 July 2013"}, {"from": "Udinese", "name": "Mehdi Benatia", "currency": "Euro", "value": 13500000, "to": "Roma", "date": "13 July 2013"}, {"from": "Roma", "name": "Valerio Verre", "currency": "Euro", "value": "Co-ownership, ", "to": "Udinese", "date": "13 July 2013"}, {"from": "Roma", "name": "Nicol\u00e1s L\u00f3pez", "currency": "Euro", "value": "Co-ownership, ", "to": "Udinese", "date": "13 July 2013"}, {"from": "Parma", "name": "Andrea Rossini", "currency": "Euro", "value": "Loan (between co-owner)", "to": "Cesena", "date": "13 July 2013"}, {"from": "Roma", "name": "\u0141ukasz Skorupski", "currency": "Euro", "value": 890000, "to": "G\u00f3rnik Zabrze", "date": "13 July 2013"}, {"from": "Parma", "name": "Francesco Finocchio", "currency": "Euro", "value": "Loan", "to": "Trapani", "date": "13 July 2013"}, {"from": "Livorno", "name": "Gast\u00f3n Cellerino", "currency": "Euro", "value": "Undisclosed", "to": "Santiago Wanderers", "date": "13 July 2013"}, {"from": "Cremonese", "name": "Alessandro Favalli", "currency": "Euro", "value": "Co-ownership", "to": "Parma", "date": "13 July 2013"}, {"from": "Internazionale", "name": "Mame Baba Thiam", "currency": "Euro", "value": "Free", "to": "Lanciano", "date": "15 July 2013"}, {"from": "Genoa", "name": "S\u00e9bastien Frey", "currency": "Euro", "value": "Undisclosed", "to": "Bursaspor", "date": "15 July 2013"}, {"from": "Napoli", "name": "Camillo Ciano", "currency": "Euro", "value": "Loan", "to": "Padova", "date": "15 July 2013"}, {"from": "Internazionale", "name": "Daniel Bessa", "currency": "Euro", "value": "Loan", "to": "Olhanense", "date": "15 July 2013"}, {"from": "Internazionale", "name": "Vid Belec", "currency": "Euro", "value": "Loan", "to": "Olhanense", "date": "15 July 2013"}, {"from": "Internazionale", "name": "Simone Pasa", "currency": "Euro", "value": "Loan", "to": "Varese", "date": "16 July 2013"}, {"from": "Chievo", "name": "Pavol Farka\u0161", "currency": "Euro", "value": "Loan", "to": "Ternana", "date": "16 July 2013"}, {"from": "Napoli", "name": "Edinson Cavani", "currency": "Euro", "value": "Undisclosed", "to": "Paris Saint-Germain", "date": "16 July 2013"}, {"from": "Genoa", "name": "Enis Nadarevic", "currency": "Euro", "value": "Loan", "to": "Cesena", "date": "16 July 2013"}, {"from": "Lyon", "name": "Luciano Fabi\u00e1n Monz\u00f3n", "currency": "Euro", "value": 3300000, "to": "Catania", "date": "16 July 2013"}, {"from": "Chievo", "name": "Sergio Viotti", "currency": "Euro", "value": "Loan", "to": "Juve Stabia", "date": "16 July 2013"}, {"from": "Atalanta", "name": "Ivan Radovanovi\u0107", "currency": "Euro", "value": "Undisclosed", "to": "Chievo", "date": "17 July 2013"}, {"from": "Atalanta", "name": "Salvatore Molina", "currency": "Euro", "value": "Loan", "to": "Modena", "date": "17 July 2013"}, {"from": "Atalanta", "name": "Doudou Mangni", "currency": "Euro", "value": "Loan", "to": "Modena", "date": "17 July 2013"}, {"from": "Catania", "name": "Edgar \u00c7ani", "currency": "Euro", "value": "Loan", "to": "Carpi", "date": "17 July 2013"}, {"from": "River Plate", "name": "Ezequiel Cirigliano", "currency": "Euro", "value": "Loan", "to": "Verona", "date": "18 July 2013"}, {"from": "Manchester City", "name": "Maicon", "currency": "Euro", "value": "Free", "to": "Roma", "date": "18 July 2013"}, {"from": "Fiorentina", "name": "Stevan Joveti\u0107", "currency": "Euro", "value": "Undisclosed", "to": "Manchester City", "date": "18 July 2013"}, {"from": "Juventus", "name": "Timothy Nocchi", "currency": "Euro", "value": "Loan", "to": "Carpi", "date": "18 July 2013"}, {"from": "Siena", "name": "Adri\u00e1n Calello", "currency": "Euro", "value": "Free", "to": "Chievo", "date": "18 July 2013"}, {"from": "Dinamo Bucure\u0219ti", "name": "Marius Alexe", "currency": "Euro", "value": "Loan", "to": "Sassuolo", "date": "18 July 2013"}, {"from": "Atalanta", "name": "Leonardo Gatto", "currency": "Euro", "value": "Loan", "to": "Lanciano", "date": "18 July 2013"}, {"from": "Udinese", "name": "Christian Battocchio", "currency": "Euro", "value": "Undisclosed", "to": "Watford", "date": "19 July 2013"}, {"from": "Udinese", "name": "Diego Fabbrini", "currency": "Euro", "value": "Undisclosed", "to": "Watford", "date": "19 July 2013"}, {"from": "Udinese", "name": "Marco Davide Faraoni", "currency": "Euro", "value": "Undisclosed", "to": "Watford", "date": "19 July 2013"}, {"from": "Udinese", "name": "Gabriele Angella", "currency": "Euro", "value": "Undisclosed", "to": "Watford", "date": "19 July 2013"}, {"from": "Udinese", "name": "Marco Cassetti", "currency": "Euro", "value": "Undisclosed", "to": "Watford", "date": "19 July 2013"}, {"from": "Udinese", "name": "Almen Abdi", "currency": "Euro", "value": "Undisclosed", "to": "Watford", "date": "19 July 2013"}, {"from": "Genoa", "name": "Panagiotis Tachtsidis", "currency": "Euro", "value": "Co-ownership", "to": "Catania", "date": "19 July 2013"}, {"from": "Catania", "name": "Francesco Lodi", "currency": "Euro", "value": "Co-ownership", "to": "Genoa", "date": "19 July 2013"}, {"from": "Napoli", "name": "Jacopo Dezi", "currency": "Euro", "value": "Loan", "to": "Crotone", "date": "19 July 2013"}, {"from": "Crotone", "name": "Alessandro Ligi", "currency": "Euro", "value": "Co-ownership", "to": "Parma", "date": "19 July 2013"}, {"from": "Crotone", "name": "Denilson Gabionetta", "currency": "Euro", "value": "Undisclosed", "to": "Parma", "date": "19 July 2013"}, {"from": "Milan", "name": "Mario Yepes", "currency": "Euro", "value": "Free", "to": "Atalanta", "date": "19 July 2013"}, {"from": "Parma", "name": "\u00c1lvaro Ampuero", "currency": "Euro", "value": "Loan", "to": "Padova", "date": "19 July 2013"}, {"from": "Sparta Prague", "name": "Manuel Pami\u0107", "currency": "Euro", "value": "Loan", "to": "Chievo", "date": "19 July 2013"}, {"from": "Fiorentina", "name": "Andrea Seculin", "currency": "Euro", "value": "Undisclosed", "to": "Chievo", "date": "19 July 2013"}, {"from": "Chievo", "name": "Andrea Seculin", "currency": "Euro", "value": "Loan", "to": "Avellino", "date": "19 July 2013"}, {"from": "PSV", "name": "Kevin Strootman", "currency": "Euro", "value": "\u20ac16.5M", "to": "Roma", "date": "19 July 2013"}, {"from": "Roma", "name": "Marquinhos", "currency": "Euro", "value": "\u20ac31.4M", "to": "Paris Saint-Germain", "date": "19 July 2013"}, {"from": "Livorno", "name": "Antonio Meola", "currency": "Euro", "value": "Loan", "to": "Paganese", "date": "19 July 2013"}, {"from": "Lazio", "name": "Modibo Diakit\u00e9", "currency": "Euro", "value": "Free", "to": "Sunderland", "date": "19 July 2013"}, {"from": "Genoa", "name": "Bo\u0161ko Jankovi\u0107", "currency": "Euro", "value": "Loan", "to": "Verona", "date": "20 July 2013"}, {"from": "Fiorentina", "name": "Diego Cenciarelli", "currency": "Euro", "value": "Co-ownership", "to": "Teramo", "date": "20 July 2013"}, {"from": "Juventus", "name": "Felipe Melo", "currency": "Euro", "value": 3750000, "to": "Galatasaray", "date": "20 July 2013"}, {"from": "Catania", "name": "Mirko Antenucci", "currency": "Euro", "value": "Loan", "to": "Ternana", "date": "20 July 2013"}, {"from": "Real Madrid", "name": "Ra\u00fal Albiol", "currency": "Euro", "value": "Undisclosed", "to": "Napoli", "date": "21 July 2013"}, {"from": "Genoa", "name": "Sebasti\u00e1n Ribas", "currency": "Euro", "value": "Loan", "to": "Barcelona S.C.", "date": "21 July 2013"}, {"from": "Internazionale", "name": "Simone Benedetti", "currency": "Euro", "value": "Loan", "to": "Padova", "date": "22 July 2013"}, {"from": "Napoli", "name": "Cristian Gabriel Ch\u00e1vez", "currency": "Euro", "value": "Undisclosed", "to": "PAS Giannina", "date": "22 July 2013"}, {"from": "Juventus", "name": "Carlo Pinsoglio", "currency": "Euro", "value": "Loan", "to": "Modena", "date": "23 July 2013"}, {"from": "Catania", "name": "Pietro Terracciano", "currency": "Euro", "value": "Loan", "to": "Avellino", "date": "23 July 2013"}, {"from": "Parma", "name": "Soufiane Bidaoui", "currency": "Euro", "value": "Loan", "to": "Crotone", "date": "23 July 2013"}, {"from": "Red Star Belgrade", "name": "Nikola Maksimovi\u0107", "currency": "Euro", "value": "Undisclosed", "to": "Torino", "date": "23 July 2013"}, {"from": "Anderlecht", "name": "Lucas Biglia", "currency": "Euro", "value": "Undisclosed", "to": "Lazio", "date": "23 July 2013"}, {"from": "Internazionale", "name": "Niccol\u00f2 Belloni", "currency": "Euro", "value": "Co-ownership", "to": "Modena", "date": "23 July 2013"}, {"from": "Palermo", "name": "Josip Ili\u010di\u0107", "currency": "Euro", "value": "Undisclosed", "to": "Fiorentina", "date": "23 July 2013"}, {"from": "Lazio", "name": "Luca Crescenzi", "currency": "Euro", "value": "Loan", "to": "Siena", "date": "23 July 2013"}, {"from": "Rosario", "name": "Nahuel Valentini", "currency": "Euro", "value": "Undisclosed", "to": "Livorno", "date": "24 July 2013"}, {"from": "Catania", "name": "Fabio Sciacca", "currency": "Euro", "value": "Loan", "to": "Ternana", "date": "24 July 2013"}, {"from": "Palermo", "name": "Giuseppe Prestia", "currency": "Euro", "value": "Free", "to": "Parma", "date": "24 July 2013"}, {"from": "Hamburger", "name": "Jacopo Sala", "currency": "Euro", "value": "Undisclosed", "to": "Verona", "date": "24 July 2013"}, {"from": "Hajduk", "name": "Josip Elez", "currency": "Euro", "value": "Undisclosed", "to": "Lazio", "date": "24 July 2013"}, {"from": "Napoli", "name": "Raffaele Maiello", "currency": "Euro", "value": "Loan", "to": "Ternana", "date": "24 July 2013"}, {"from": "Chievo", "name": "Yohan Tavares", "currency": "Euro", "value": "Undisclosed", "to": "Estoril", "date": "25 July 2013"}, {"from": "Napoli", "name": "Morgan De Sanctis", "currency": "Euro", "value": 500000, "to": "Roma", "date": "25 July 2013"}, {"from": "Livorno", "name": "Mirko Bigazzi", "currency": "Euro", "value": "Loan", "to": "Olhanense", "date": "25 July 2013"}, {"from": "Torino", "name": "Nicol\u00e1s Gorobsov", "currency": "Euro", "value": "Loan", "to": "Timi\u015foara", "date": "25 July 2013"}, {"from": "Lazio", "name": "Mauro Z\u00e1rate", "currency": "Euro", "value": "Free", "to": "V\u00e9lez", "date": "26 July 2013"}, {"from": "Internazionale", "name": "Gianmarco Gabbianelli", "currency": "Euro", "value": "Co-ownership", "to": "Pro Patria", "date": "26 July 2013"}, {"from": "Internazionale", "name": "Diego Mella", "currency": "Euro", "value": "Loan", "to": "Pro Patria", "date": "26 July 2013"}, {"from": "Internazionale", "name": "Bocar Djumo", "currency": "Euro", "value": "Loan", "to": "Uni\u00e3o", "date": "26 July 2013"}, {"from": "Chievo", "name": "Santiago Morero", "currency": "Euro", "value": "Free", "to": "Siena", "date": "26 July 2013"}, {"from": "Palermo", "name": "Francesco Benussi", "currency": "Euro", "value": "Free", "to": "Udinese", "date": "26 July 2013"}, {"from": "Catania", "name": "Giuseppe Messina", "currency": "Euro", "value": "Co-ownership", "to": "Pro Patria", "date": "26 July 2013"}, {"from": "Catania", "name": "Gianluca Maran", "currency": "Euro", "value": "Co-ownership", "to": "Bassano", "date": "26 July 2013"}, {"from": "Catania", "name": "Fabio Aveni", "currency": "Euro", "value": "Loan", "to": "Perugia", "date": "26 July 2013"}, {"from": "Parma", "name": "Gennaro Scognamiglio", "currency": "Euro", "value": "Loan", "to": "Perugia", "date": "26 July 2013"}, {"from": "Parma", "name": "Francesco Modesto", "currency": "Euro", "value": "Undisclosed", "to": "Padova", "date": "26 July 2013"}, {"from": "Padova", "name": "Bruno Leonardo Vicente", "currency": "Euro", "value": "Undisclosed", "to": "Parma", "date": "26 July 2013"}, {"from": "Genoa", "name": "Vincenzo Rennella", "currency": "Euro", "value": "Undisclosed", "to": "Betis", "date": "26 July 2013"}, {"from": "Real Madrid", "name": "Gonzalo Higua\u00edn", "currency": "Euro", "value": "Undisclosed", "to": "Napoli", "date": "27 July 2013"}, {"from": "Milan", "name": "Rodney Strasser", "currency": "Euro", "value": "Undisclosed", "to": "Genoa", "date": "27 July 2013"}, {"from": "Genoa", "name": "K\u00e9vin Constant", "currency": "Euro", "value": "Co-ownership resolution", "to": "Milan", "date": "27 July 2013"}, {"from": "Verona", "name": "Lapis Kiakis", "currency": "Euro", "value": "Loan", "to": "Carpi", "date": "27 July 2013"}, {"from": "Udinese", "name": "Juan Surraco", "currency": "Euro", "value": "Undisclosed", "to": "Modena", "date": "28 July 2013"}, {"from": "Liverpool", "name": "Pepe Reina", "currency": "Euro", "value": "Loan", "to": "Napoli", "date": "29 July 2013"}, {"from": "Lecce", "name": "Cosimo Chiric\u00f2", "currency": "Euro", "value": "Co-ownership", "to": "Parma", "date": "29 July 2013"}, {"from": "Parma", "name": "Cosimo Chiric\u00f2", "currency": "Euro", "value": "Loan", "to": "Latina", "date": "29 July 2013"}, {"from": "Olympiacos", "name": "Leandro Greco", "currency": "Euro", "value": "Undisclosed", "to": "Livorno", "date": "30 July 2013"}, {"from": "Napoli", "name": "Mario Santana", "currency": "Euro", "value": "Undisclosed", "to": "Genoa", "date": "30 July 2013"}, {"from": "Juventus", "name": "Nicola Leali", "currency": "Euro", "value": "Loan", "to": "Spezia", "date": "30 July 2013"}, {"from": "Torino", "name": "Abou Diop", "currency": "Euro", "value": "Loan", "to": "Juve Stabia", "date": "30 July 2013"}, {"from": "Roma", "name": "Simone Sini", "currency": "Euro", "value": "Co-ownership", "to": "Perugia", "date": "30 July 2013"}, {"from": "Siena", "name": "Marcelo Larrondo", "currency": "Euro", "value": "Co-ownership", "to": "Torino", "date": "31 July 2013"}, {"from": "Empoli", "name": "Elvis Kabashi", "currency": "Euro", "value": "Undisclosed", "to": "Juventus", "date": "31 July 2013"}, {"from": "Empoli", "name": "Daniele Rugani", "currency": "Euro", "value": "Co-ownership", "to": "Juventus", "date": "31 July 2013"}, {"from": "Juventus", "name": "Daniele Rugani", "currency": "Euro", "value": "Loan", "to": "Empoli", "date": "31 July 2013"}, {"from": "Sampdoria", "name": "Gianni Munari", "currency": "Euro", "value": "Undisclosed", "to": "Parma", "date": "31 July 2013"}, {"from": "Napoli", "name": "Luigi Sepe", "currency": "Euro", "value": "Loan", "to": "Virtus Lanciano", "date": "31 July 2013"}, {"from": "Hoffenheim", "name": "Afriyie Acquah", "currency": "Euro", "value": "Loan", "to": "Parma", "date": "31 July 2013"}]