{"fc-barcelona": ["Busquets", "Pedro", "Borja G\u00c3\u00b3mez", "Mart\u00c3\u00adn Montoya", "Xavi", "Lionel Messi", "David Villa", "Puyol", "Jordi Alba", "Dani Alves", "Iniesta", "Cristian Tello", "Alexis S\u00c3\u00a1nchez", "Piqu\u00c3\u00a9", "Adriano", "Alex Song", "Thiago", "Cesc F\u00c3\u00a0bregas"], "malaga-cf": ["Eliseu", "Duda", "Joaqu\u00c3\u00adn", "Javier Saviola", "Diego Lugano", "J\u00c3\u00balio Baptista", "Nacho Monreal", "Isco", "Diego Buonanotte", "Sergio S\u00c3\u00a1nchez", "Portillo", "Mart\u00c3\u00adn Demichelis", "Lucas Piaz\u00c3\u00b3n", "Roque Santa Cruz", "Camacho", "Antunes", "Pedro Morales", "Jes\u00c3\u00bas G\u00c3\u00a1mez", "J\u00c3\u00a9r\u00c3\u00a9my Toulalan", "Fabrice Olinga", "Juanmi", "Weligton"], "athletic-bilbao": ["Aduriz", "I\u00c3\u00b1igo P\u00c3\u00a9rez", "Muniain", "Gurpegi", "Iraola", "Susaeta", "Aurtenetxe", "San Jos\u00c3\u00a9", "Iturraspe", "Ruiz de Galarreta", "Ander Herrera", "Ibai", "Llorente", "De Marcos"], "valencia-cf": ["Parejo", "\u00c3\u0089ver Banega", "J\u00c3\u00a9r\u00c3\u00a9my Mathieu", "Sofiane F\u00c3\u00a9ghouli", "Aly Cissokho", "Jo\u00c3\u00a3o Pereira", "Canales", "Soldado", "Jonathan Viera", "Andr\u00c3\u00a9s Guardado", "Adil Rami", "Ricardo Costa", "Jonas", "Pablo Piatti", "Tino Costa", "V\u00c3\u00adctor Ruiz", "Nelson Valdez", "Juan Bernat"], "celta-vigo": ["Bermejo", "Fabi\u00c3\u00a1n Orellana", "Toni", "Chu-Young Park", "Roberto Lago", "Iago Aspas", "De Lucas", "\u00c3\u0081lex L\u00c3\u00b3pez", "Borja Oubi\u00c3\u00b1a", "Augusto Fern\u00c3\u00a1ndez", "Michael Krohn-Dehli", "Natxo Insa", "Gustavo Cabral"], "real-betis": ["Rub\u00c3\u00a9n Castro", "Salva Sevilla", "\u00c3\u0081lex Mart\u00c3\u00adnez", "Dorlan Pab\u00c3\u00b3n", "Jorge Molina", "Ca\u00c3\u00b1as", "\u00c3\u008d\u00c3\u00b1igo L\u00c3\u00b3pez", "Nosa Igiebor", "Nacho", "Paul\u00c3\u00a3o", "Mario", "Salvador Agra", "Pozuelo", "Juankar", "Javi Chica", "Be\u00c3\u00b1at", "\u00c3\u0081lvaro Vadillo", "Rub\u00c3\u00a9n P\u00c3\u00a9rez", "\u00c3\u0081ngel L\u00c3\u00b3pez", "Joel Campbell", "Jonathan Pereira"], "granada-cf": ["Mainz", "Aranda", "Fabi\u00c3\u00a1n Orellana", "Odion Ighalo", "Antonio Floro Flores", "Youssef El-Arabi", "Jaime", "Roberto", "Recio", "Juanma Ortiz", "Allan Nyom", "Yacine Brahimi", "Dani Ben\u00c3\u00adtez", "Gabriel Torje", "Nolito", "Mikel Rico", "Brayan Angulo", "Siqueira", "Diego Buonanotte"], "real-valladolid": ["\u00c3\u0093scar", "Bueno", "Baraja", "Omar Ramos", "V\u00c3\u00adctor P\u00c3\u00a9rez", "Patrick Ebert", "Javi Guerra", "Daniel Larsson", "Manucho", "Pe\u00c3\u00b1a", "Antonio Rukavina", "Sastre", "\u00c3\u0081lvaro Rubio", "Balenziaga", "Rub\u00c3\u00a9n"], "rcd-mallorca": ["Arizmendi", "Antonio Luna", "Micka\u00c3\u00abl Pereira", "Javi M\u00c3\u00a1rquez", "Pina", "Bigas", "V\u00c3\u00adctor Casades\u00c3\u00bas", "Tomer Hemed", "Dudu Aouate", "Geromel", "Mart\u00c3\u00ad", "Emilio N'Sue", "Giovani Dos Santos", "Kevin", "Alfaro"], "atletico-madrid": ["Koke", "Diego Costa", "Mario Su\u00c3\u00a1rez", "Miranda", "Arda Turan", "Diego God\u00c3\u00adn", "Emir Spahi\u00c4\u0087", "Ra\u00c3\u00bal Garc\u00c3\u00ada", "Filipe Lu\u00c3\u00ads", "Emre Bel\u00c3\u00b6zo\u00c4\u009flu", "Manquillo", "Gabi", "Dani Aquino", "Emiliano Ins\u00c3\u00baa", "Cristian Rodr\u00c3\u00adguez", "Juanfran", "Tiago", "Radamel Falcao", "Adri\u00c3\u00a1n"], "espanyol-barcelona": ["Javi L\u00c3\u00b3pez", "Baena", "\u00c3\u0081lvaro", "Sergio Tejera", "Diego Colotto", "Verd\u00c3\u00ba", "Christian Stuani", "Wakaso Mubarak", "Juan Alb\u00c3\u00adn", "H\u00c3\u00a9ctor Moreno", "Sim\u00c3\u00a3o", "Sergio Garc\u00c3\u00ada", "V\u00c3\u00adctor \u00c3\u0081lvarez", "Cristian G\u00c3\u00b3mez", "V\u00c3\u00adctor S\u00c3\u00a1nchez", "Juan Forl\u00c3\u00adn", "Samuele Longo"], "deportivo-la-coruna": ["Camu\u00c3\u00b1as", "Juan Dom\u00c3\u00adnguez", "N\u00c3\u00a9lson Oliveira", "Bruno Gama", "Abel Aguilar", "Aythami Artiles", "Bodipo", "S\u00c3\u00adlvio", "Riki", "Diogo Salom\u00c3\u00a3o", "Valer\u00c3\u00b3n", "\u00c3\u0081lex", "Pizzi", "Laure", "Manuel Pablo", "Marchena", "Evaldo"], "real-zaragoza": ["\u00c3\u0081lvaro Gonz\u00c3\u00a1lez", "Rodri", "Rub\u00c3\u00a9n Rochina", "Paco Monta\u00c3\u00b1\u00c3\u00a9s", "Movilla", "H\u00c3\u00a9lder Postiga", "V\u00c3\u00adctor", "Franco Zuculini", "Henri Bienvenu", "Cristian S\u00c4\u0083punaru", "Abraham", "Romaric", "Fern\u00c3\u00a1ndez", "Apo\u00c3\u00b1o"], "rayo-vallecano": ["Nacho", "Adri\u00c3\u00a1n", "Trashorras", "Casado", "Leo Baptist\u00c3\u00a3o", "Andrija Deliba\u00c5\u00a1i\u00c4\u0087", "Tito", "Alejandro Dom\u00c3\u00adnguez", "Piti", "Javi Fuego", "Jordi Amat", "Jordi Figueras", "Alhassane Bangoura", "Jos\u00c3\u00a9 Carlos", "Ra\u00c3\u00bal Tamudo", "Franco V\u00c3\u00a1zquez"], "getafe-cf": ["Abdelaziz Barrada", "Valera", "Medhi Lacen", "\u00c3\u0081lvaro", "Lafita", "Diego Castro", "Man\u00c3\u00a9", "Federico Fern\u00c3\u00a1ndez", "Colunga", "Alexis", "Juan Rodr\u00c3\u00adguez", "Pedro Le\u00c3\u00b3n", "Escudero", "Pablo Sarabia", "Lopo Garc\u00c3\u00ada", "Borja", "Paco Alc\u00c3\u00a1cer", "Xavi Torres", "Gavil\u00c3\u00a1n", "Rafa"], "real-sociedad": ["Javi L\u00c3\u00b3pez", "Antoine Griezmann", "Zurutuza", "Diego Ifr\u00c3\u00a1n", "Elustondo", "Chory Castro", "Xabi Prieto", "I\u00c3\u00b1igo Mart\u00c3\u00adnez", "Carlos Mart\u00c3\u00adnez", "De la Bella", "Illarra", "Rub\u00c3\u00a9n Pardo", "Carlos Vela", "Jos\u00c3\u00a9 \u00c3\u0081ngel", "Ivan Rakiti\u00c4\u0087", "Bergara", "Mikel", "Agirretxe"], "levante-ud": ["Theofanis Gekas", "\u00c3\u0081ngel", "Ra\u00c3\u00bal Rodr\u00c3\u00adguez", "Valdo", "Juanfran", "Christian Lell", "Pedro R\u00c3\u00ados", "Iborra", "Pedro L\u00c3\u00b3pez", "Juanlu", "Rub\u00c3\u00a9n Garc\u00c3\u00ada", "Navarro", "Ballesteros", "Obafemi Martins", "Nabil El Zhar", "Roger", "Gustavo Mun\u00c3\u00baa", "M\u00c3\u00adchel", "Barkero", "Robert Acquafresca", "Nikos Karabelas"], "ca-osasuna": ["Cejudo", "Arribas", "Francisco Silva", "Pu\u00c3\u00b1al", "Roberto Torres", "Roland Lamah", "Lolo", "Manuel Onwu", "David Timor", "Emiliano Armenteros", "De las Cuevas", "Dami\u00c3\u00a1", "Kike Sola", "Llorente", "Masoud Shojaei", "Marc Bertr\u00c3\u00a1n", "Nino", "Raoul Lo\u00c3\u00a9"], "sevilla-fc": ["Emir Spahi\u00c4\u0087", "Alberto Bot\u00c3\u00ada", "Jes\u00c3\u00bas Navas", "Coke", "Piotr Trochowski", "Gary Medel", "Cicinho", "Manu del Moral", "Alberto Moreno", "Ivan Rakiti\u00c4\u0087", "Federico Fazio", "Geoffrey Kondogbia", "Reyes", "\u00c3\u0081lvaro Negredo"], "real-madrid": ["Luka Modri\u00c4\u0087", "Kak\u00c3\u00a1", "Karim Benzema", "Fabinho", "\u00c3\u0081ngel Di Mar\u00c3\u00ada", "Arbeloa", "Michael Essien", "Sergio Ramos", "Pepe", "Mesut \u00c3\u0096zil", "Sergio S\u00c3\u00a1nchez", "Ricardo Carvalho", "F\u00c3\u00a1bio Coentr\u00c3\u00a3o", "Sami Khedira", "Gonzalo Higua\u00c3\u00ad\u00c2\u00adn", "Jos\u00c3\u00a9 Callej\u00c3\u00b3n", "Ra\u00c3\u00bal Albiol", "Morata", "Cristiano Ronaldo", "Xabi Alonso"]}